[
  {
    "date": "2026-02-19",
    "strong": 6,
    "potential": 6,
    "total": 12
  },
  {
    "date": "2026-02-18",
    "strong": 6,
    "potential": 6,
    "total": 12
  },
  {
    "date": "2026-02-17",
    "strong": 6,
    "potential": 6,
    "total": 12
  },
  {
    "date": "2026-02-14",
    "strong": 6,
    "potential": 6,
    "total": 12
  },
  {
    "date": "2026-02-13",
    "strong": 5,
    "potential": 6,
    "total": 11
  },
  {
    "date": "2026-02-12",
    "strong": 6,
    "potential": 6,
    "total": 12
  },
  {
    "date": "2026-02-11",
    "strong": 6,
    "potential": 6,
    "total": 12
  },
  {
    "date": "2026-02-10",
    "strong": 6,
    "potential": 6,
    "total": 12
  },
  {
    "date": "2026-02-07",
    "strong": 6,
    "potential": 6,
    "total": 12
  },
  {
    "date": "2026-02-06",
    "strong": 6,
    "potential": 6,
    "total": 12
  },
  {
    "date": "2026-01-21",
    "strong": 1,
    "potential": 6,
    "total": 7
  },
  {
    "date": "2026-01-20",
    "strong": 1,
    "potential": 6,
    "total": 7
  },
  {
    "date": "2026-01-17",
    "strong": 0,
    "potential": 6,
    "total": 6
  },
  {
    "date": "2026-01-16",
    "strong": 3,
    "potential": 6,
    "total": 9
  },
  {
    "date": "2026-01-15",
    "strong": 1,
    "potential": 6,
    "total": 7
  },
  {
    "date": "2026-01-14",
    "strong": 4,
    "potential": 6,
    "total": 10
  },
  {
    "date": "2026-01-13",
    "strong": 3,
    "potential": 6,
    "total": 9
  },
  {
    "date": "2026-01-10",
    "strong": 2,
    "potential": 6,
    "total": 8
  },
  {
    "date": "2026-01-09",
    "strong": 1,
    "potential": 6,
    "total": 7
  },
  {
    "date": "2026-01-08",
    "strong": 2,
    "potential": 6,
    "total": 8
  },
  {
    "date": "2026-01-07",
    "strong": 2,
    "potential": 6,
    "total": 8
  },
  {
    "date": "2026-01-06",
    "strong": 4,
    "potential": 6,
    "total": 10
  },
  {
    "date": "2026-01-03",
    "strong": 0,
    "potential": 6,
    "total": 6
  },
  {
    "date": "2026-01-02",
    "strong": 2,
    "potential": 6,
    "total": 8
  },
  {
    "date": "2026-01-01",
    "strong": 1,
    "potential": 6,
    "total": 7
  },
  {
    "date": "2025-12-31",
    "strong": 1,
    "potential": 6,
    "total": 7
  },
  {
    "date": "2025-12-30",
    "strong": 0,
    "potential": 6,
    "total": 6
  },
  {
    "date": "2025-12-27",
    "strong": 2,
    "potential": 6,
    "total": 8
  },
  {
    "date": "2025-12-26",
    "strong": 2,
    "potential": 6,
    "total": 8
  },
  {
    "date": "2025-12-25",
    "strong": 1,
    "potential": 6,
    "total": 7
  }
]